CHANGES.txt
LICENSE.txt
MANIFEST.in
README.txt
setup.py
js/__init__.py
js.jquery_datalink.egg-info/PKG-INFO
js.jquery_datalink.egg-info/SOURCES.txt
js.jquery_datalink.egg-info/dependency_links.txt
js.jquery_datalink.egg-info/entry_points.txt
js.jquery_datalink.egg-info/namespace_packages.txt
js.jquery_datalink.egg-info/not-zip-safe
js.jquery_datalink.egg-info/requires.txt
js.jquery_datalink.egg-info/top_level.txt
js/jquery_datalink/__init__.py
js/jquery_datalink/test_jquery_datalink.txt
js/jquery_datalink/resources/README.txt
js/jquery_datalink/resources/jquery.datalink.js