Metadata-Version: 1.0
Name: js.jquery-datalink
Version: 1.0.0
Summary: Fanstatic packaging of jQuery Datalink
Home-page: UNKNOWN
Author: Fanstatic Developers
Author-email: fanstatic@googlegroups.com
License: BSD
Platform: UNKNOWN
